PyCgame/__init__.py
PyCgame/creations/spaceattacks/main.py
PyCgame/creations/spaceattacks/spaceattacks.gif
PyCgame/creations/spaceattacks/spaceattacks.mp4
PyCgame/creations/spaceattacks/assets/degat.wav
PyCgame/creations/spaceattacks/assets/explosion 1.png
PyCgame/creations/spaceattacks/assets/explosion 2.png
PyCgame/creations/spaceattacks/assets/explosion 3.png
PyCgame/creations/spaceattacks/assets/explosion 4.png
PyCgame/creations/spaceattacks/assets/explosion.wav
PyCgame/creations/spaceattacks/assets/fond.png
PyCgame/creations/spaceattacks/assets/monstre 1.png
PyCgame/creations/spaceattacks/assets/monstre 2.png
PyCgame/creations/spaceattacks/assets/monstre 3.png
PyCgame/creations/spaceattacks/assets/monstre 4.png
PyCgame/creations/spaceattacks/assets/monstre 5.png
PyCgame/creations/spaceattacks/assets/monstre 6.png
PyCgame/creations/spaceattacks/assets/projectile 1.png
PyCgame/creations/spaceattacks/assets/projectile 2.png
PyCgame/creations/spaceattacks/assets/projectile 3.png
PyCgame/creations/spaceattacks/assets/tir.wav
PyCgame/creations/spaceattacks/assets/vaisseau 1.png
PyCgame/creations/spaceattacks/assets/vaisseau 2.png
PyCgame/creations/spaceattacks/assets/vaisseau 3.png
PyCgame/creations/spaceattacks/assets/vaisseau 4.png
PyCgame/creations/spaceattacks/assets/police/100.png
PyCgame/creations/spaceattacks/assets/police/101.png
PyCgame/creations/spaceattacks/assets/police/102.png
PyCgame/creations/spaceattacks/assets/police/103.png
PyCgame/creations/spaceattacks/assets/police/104.png
PyCgame/creations/spaceattacks/assets/police/105.png
PyCgame/creations/spaceattacks/assets/police/106.png
PyCgame/creations/spaceattacks/assets/police/107.png
PyCgame/creations/spaceattacks/assets/police/108.png
PyCgame/creations/spaceattacks/assets/police/109.png
PyCgame/creations/spaceattacks/assets/police/110.png
PyCgame/creations/spaceattacks/assets/police/111.png
PyCgame/creations/spaceattacks/assets/police/112.png
PyCgame/creations/spaceattacks/assets/police/113.png
pycgame-1.8.0.dist-info/METADATA
pycgame-1.8.0.dist-info/WHEEL
pycgame-1.8.0.dist-info/entry_points.txt
pycgame-1.8.0.dist-info/top_level.txt
pycgame-1.8.0.dist-info/RECORD
